ops/__init__.py
ops/constants.py
ops/release.py
ops/cli/__init__.py
ops/cli/ops.py
ops/cli/arguments/__init__.py
ops/cli/arguments/option_helpers.py
ops/entities/__init__.py
ops/entities/docker/c++/Dockerfile
ops/entities/docker/npm/Dockerfile
ops/entities/docker/python/Dockerfile
ops/entities/docker/springboot/Dockerfile
ops/entities/gitlab/django/gitlab-ci.yml
ops/entities/gitlab/docker/gitlab-ci.yml
ops/entities/gitlab/gradle/gitlab-ci.yml
ops/entities/gitlab/maven/gitlab-ci.yml
ops/entities/gitlab/npm/gitlab-ci.yml
ops/entities/jenkins/django/Jenkinsfile.groovy
ops/entities/jenkins/docker/Jenkinsfile.groovy
ops/entities/jenkins/gradle/Jenkinsfile.groovy
ops/entities/jenkins/maven/Jenkinsfile.groovy
ops/entities/jenkins/npm/Jenkinsfile.groovy
ops/entities/jenkins/sonarqube/Jenkinsfile.groovy
ops/errors/__init__.py
ops/utils/__init__.py
ops/utils/color.py
ops/utils/display.py
ops/utils/singleton.py
ops/utils/text/__init__.py
ops/utils/text/converters.py
quickops-1.1.2.dist-info/METADATA
quickops-1.1.2.dist-info/WHEEL
quickops-1.1.2.dist-info/entry_points.txt
quickops-1.1.2.dist-info/top_level.txt
quickops-1.1.2.dist-info/RECORD
