Metadata-Version: 2.1
Name: quickops
Version: 1.1.2
Home-page: https://github.com/piksida/ops
Requires-Dist: cowsay
Requires-Dist: importlib.resources
